aext_share_notebook_server/__init__.py
aext_share_notebook_server-0.0.1.dist-info/METADATA
aext_share_notebook_server-0.0.1.dist-info/WHEEL
aext_share_notebook_server-0.0.1.dist-info/RECORD
