Metadata-Version: 2.1
Name: aext-share-notebook-server
Version: 0.0.1
Summary: The aext-share-notebook-server component of anaconda-toolbox
License-Expression: BSD-3-Clause
